gt3x/__init__.py
gt3x/gt3x_functions.py
gt3x/main.py
gt3x_muschellij2-0.0.2.dist-info/LICENSE
gt3x_muschellij2-0.0.2.dist-info/METADATA
gt3x_muschellij2-0.0.2.dist-info/WHEEL
gt3x_muschellij2-0.0.2.dist-info/top_level.txt
gt3x_muschellij2-0.0.2.dist-info/RECORD
