Metadata-Version: 2.1
Name: gt3x-muschellij2
Version: 0.0.2
Summary: A package to read extract raw acceleration data from .gt3x files.
Home-page: https://github.com/shaheen-syed/gt3x
Author: Shaheen Syed
Author-email: shaheen.syed@uit.no
License: MIT
Platform: UNKNOWN
Classifier: Programming Language :: Python :: 3
Classifier: License :: OSI Approved :: MIT License
Classifier: Operating System :: OS Independent
Requires-Python: >=3.6
